apis/inference/v1/image_pb2.py
apis/inference/v1/image_pb2.pyi
apis/inference/v1/image_pb2_grpc.py
apis/inference/v1/infer_pb2.py
apis/inference/v1/infer_pb2.pyi
apis/inference/v1/infer_pb2_grpc.py
apis/inference/v1/open_inference_pb2.py
apis/inference/v1/open_inference_pb2.pyi
apis/inference/v1/open_inference_pb2_grpc.py
msir_infer-0.1.0.dist-info/METADATA
msir_infer-0.1.0.dist-info/WHEEL
msir_infer-0.1.0.dist-info/RECORD
